src/__init__.py
src/read.py
chart_files-0.0.1.dist-info/LICENSE
chart_files-0.0.1.dist-info/METADATA
chart_files-0.0.1.dist-info/WHEEL
chart_files-0.0.1.dist-info/top_level.txt
chart_files-0.0.1.dist-info/RECORD
