Metadata-Version: 2.1
Name: chart-files
Version: 0.0.1
Summary: Work with chart files from various VSRG.
Home-page: https://github.com/sxturndev/chart-files
Author: sxturndev
Author-email: sxturndev@protonmail.com
Keywords: python,VSRG,library,Rhythm Game
Classifier: Development Status :: 1 - Planning
Classifier: Intended Audience :: Developers
Classifier: Programming Language :: Python :: 3
Classifier: License :: OSI Approved :: MIT License
Classifier: Operating System :: Unix
Classifier: Operating System :: MacOS :: MacOS X
Classifier: Operating System :: Microsoft :: Windows
License-File: LICENSE
